odoo/addons/fleet_vehicle_category/README.rst
odoo/addons/fleet_vehicle_category/__init__.py
odoo/addons/fleet_vehicle_category/__manifest__.py
odoo/addons/fleet_vehicle_category/models/__init__.py
odoo/addons/fleet_vehicle_category/models/fleet_vehicle.py
odoo/addons/fleet_vehicle_category/models/fleet_vehicle_category.py
odoo/addons/fleet_vehicle_category/readme/CONTRIBUTORS.rst
odoo/addons/fleet_vehicle_category/readme/DESCRIPTION.rst
odoo/addons/fleet_vehicle_category/readme/HISTORY.rst
odoo/addons/fleet_vehicle_category/security/ir.model.access.csv
odoo/addons/fleet_vehicle_category/static/description/icon.png
odoo/addons/fleet_vehicle_category/static/description/index.html
odoo/addons/fleet_vehicle_category/views/fleet_vehicle_views.xml
odoo13_addon_fleet_vehicle_category-13.0.1.0.0.dist-info/METADATA
odoo13_addon_fleet_vehicle_category-13.0.1.0.0.dist-info/WHEEL
odoo13_addon_fleet_vehicle_category-13.0.1.0.0.dist-info/top_level.txt
odoo13_addon_fleet_vehicle_category-13.0.1.0.0.dist-info/RECORD
