Metadata-Version: 2.1
Name: odoo13-addon-fleet-vehicle-category
Version: 13.0.1.0.0
Summary: Add category definition for vehicles.
Home-page: https://github.com/OCA/fleet
Author: Stefano Consolaro, Associazione PNLUG - Gruppo Odoo, Odoo Community Association (OCA)
Author-email: support@odoo-community.org
License: AGPL-3
Platform: UNKNOWN
Classifier: Programming Language :: Python
Classifier: Framework :: Odoo
Classifier: License :: OSI Approved :: GNU Affero General Public License v3
Requires-Python: >=3.5
Requires-Dist: odoo (<13.1dev,>=13.0a)
